{
  "posts": [
    {
      "id": "1",
      "user": {
        "id": "1",
        "name": "alice_92",
        "avatarThumb": "https://storage.googleapis.com/myinsta-6fc59.firebasestorage.app/ProfilePics/pexels-a-darmel-7322232.jpg"
      },
      "caption": "Beautiful scenery!",
      "media": [
        {
          "url": "https://storage.googleapis.com/myinsta-6fc59.firebasestorage.app/13280169_960_540_25fps.mp4",
          "type": "video",
          "resolution": "960x540"
        }
      ],
      "likes": 150,
      "comments": [
        {
          "user": {
            "id": "1",
            "name": "alice_92",
            "avatarThumb": "https://storage.googleapis.com/myinsta-6fc59.firebasestorage.app/ProfilePics/pexels-a-darmel-7322232.jpg"
          },
          "text": "Amazing view!"
        },
        {
          "user": {
            "id": "2",
            "name": "mark_t",
            "avatarThumb": "https://storage.googleapis.com/myinsta-6fc59.firebasestorage.app/ProfilePics/pexels-alohaphotostudio-4890259.jpg"
          },
          "text": "Where is this?"
        }
      ]
    },
    {
      "id": "2",
      "user": {
        "id": "3",
        "name": "travel_lover",
        "avatarThumb": "https://storage.googleapis.com/myinsta-6fc59.firebasestorage.app/ProfilePics/pexels-anastasia-shuraeva-5704849.jpg"
      },
      "caption": "Epic adventure!",
      "media": [
        {
          "url": "https://storage.googleapis.com/myinsta-6fc59.firebasestorage.app/236316_small.mp4",
          "type": "video",
          "resolution": "960x540"
        }
      ],
      "likes": 220,
      "comments": [
        {
          "user": {
            "id": "4",
            "name": "jake_smith",
            "avatarThumb": "https://storage.googleapis.com/myinsta-6fc59.firebasestorage.app/ProfilePics/pexels-anastasia-shuraeva-6608313.jpg"
          },
          "text": "Wow, stunning!"
        },
        {
          "user": {
            "id": "5",
            "name": "sara_w",
            "avatarThumb": "https://storage.googleapis.com/myinsta-6fc59.firebasestorage.app/ProfilePics/pexels-arthousestudio-4571943.jpg"
          },
          "text": "Love this clip!"
        }
      ]
    },
    {
      "id": "3",
      "user": {
        "id": "6",
        "name": "explorer",
        "avatarThumb": "https://storage.googleapis.com/myinsta-6fc59.firebasestorage.app/ProfilePics/pexels-arthousestudio-4640886.jpg"
      },
      "caption": "Sunset vibes!",
      "media": [
        {
          "url": "https://storage.googleapis.com/myinsta-6fc59.firebasestorage.app/istockphoto-2031340689-1024x1024.jpg",
          "type": "image",
          "resolution": "1024x1024"
        },
        {
          "url": "https://storage.googleapis.com/myinsta-6fc59.firebasestorage.app/istockphoto-2062823466-640_adpp_is.mp4",
          "type": "video",
          "resolution": "640x360"
        }
      ],
      "likes": 340,
      "comments": [
        {
          "user": {
            "id": "7",
            "name": "emma_r",
            "avatarThumb": "https://storage.googleapis.com/myinsta-6fc59.firebasestorage.app/ProfilePics/pexels-darina-belonogova-7897152.jpg"
          },
          "text": "Perfect shot!"
        },
        {
          "user": {
            "id": "8",
            "name": "lucas_g",
            "avatarThumb": "https://storage.googleapis.com/myinsta-6fc59.firebasestorage.app/ProfilePics/pexels-darina-belonogova-7897404.jpg"
          },
          "text": "Love the colors!"
        }
      ]
    },
    {
      "id": "4",
      "user": {
        "id": "9",
        "name": "foodie_girl",
        "avatarThumb": "https://storage.googleapis.com/myinsta-6fc59.firebasestorage.app/ProfilePics/pexels-guilhermealmeida-1858175.jpg"
      },
      "caption": "Delicious meal!",
      "media": [
        {
          "url": "https://storage.googleapis.com/myinsta-6fc59.firebasestorage.app/istockphoto-2130313924-1024x1024.jpg",
          "type": "image",
          "resolution": "1024x1024"
        },
        {
          "url": "https://storage.googleapis.com/myinsta-6fc59.firebasestorage.app/istockphoto-2119732310-640_adpp_is.mp4",
          "type": "video",
          "resolution": "640x360"
        }
      ],
      "likes": 180,
      "comments": [
        {
          "user": {
            "id": "10",
            "name": "michael_king",
            "avatarThumb": "https://storage.googleapis.com/myinsta-6fc59.firebasestorage.app/ProfilePics/pexels-iamikeee-2709388.jpg"
          },
          "text": "Yummy!"
        },
        {
          "user": {
            "id": "11",
            "name": "anna_b",
            "avatarThumb": "https://storage.googleapis.com/myinsta-6fc59.firebasestorage.app/ProfilePics/pexels-julia-volk-5270669.jpg"
          },
          "text": "I need this recipe!"
        }
      ]
    },
    {
      "id": "5",
      "user": {
        "id": "12",
        "name": "nature_enthusiast",
        "avatarThumb": "https://storage.googleapis.com/myinsta-6fc59.firebasestorage.app/ProfilePics/pexels-karleykosmos-4902634.jpg"
      },
      "caption": "A walk in the wild!",
      "media": [
        {
          "url": "https://storage.googleapis.com/myinsta-6fc59.firebasestorage.app/istockphoto-2154332662-640_adpp_is.mp4",
          "type": "video",
          "resolution": "640x360"
        },
        {
          "url": "https://storage.googleapis.com/myinsta-6fc59.firebasestorage.app/istockphoto-2162033406-1024x1024.jpg",
          "type": "image",
          "resolution": "1024x1024"
        }
      ],
      "likes": 275,
      "comments": [
        {
          "user": {
            "id": "13",
            "name": "ryan_m",
            "avatarThumb": "https://storage.googleapis.com/myinsta-6fc59.firebasestorage.app/ProfilePics/pexels-ketut-subiyanto-4350178.jpg"
          },
          "text": "Breathtaking!"
        },
        {
          "user": {
            "id": "14",
            "name": "julia_w",
            "avatarThumb": "https://storage.googleapis.com/myinsta-6fc59.firebasestorage.app/ProfilePics/pexels-leeloothefirst-4542178.jpg"
          },
          "text": "Nature is healing!"
        }
      ]
    },
    {
      "id": "6",
      "user": {
        "id": "15",
        "name": "adventurer",
        "avatarThumb": "https://storage.googleapis.com/myinsta-6fc59.firebasestorage.app/ProfilePics/pexels-picturesbyamusan-7204273.jpg"
      },
      "caption": "Exploring the unknown!",
      "media": [
        {
          "url": "https://storage.googleapis.com/myinsta-6fc59.firebasestorage.app/istockphoto-2154872940-1024x1024.jpg",
          "type": "image",
          "resolution": "1024x1024"
        },
        {
          "url": "https://storage.googleapis.com/myinsta-6fc59.firebasestorage.app/istockphoto-2155734323-1024x1024.jpg",
          "type": "image",
          "resolution": "1024x1024"
        },
        {
          "url": "https://storage.googleapis.com/myinsta-6fc59.firebasestorage.app/istockphoto-2155960411-640_adpp_is.mp4",
          "type": "video",
          "resolution": "640x360"
        }
      ],
      "likes": 300,
      "comments": [
        {
          "user": {
            "id": "16",
            "name": "chris_p",
            "avatarThumb": "https://storage.googleapis.com/myinsta-6fc59.firebasestorage.app/ProfilePics/pexels-rdne-7402883.jpg"
          },
          "text": "Incredible journey!"
        },
        {
          "user": {
            "id": "17",
            "name": "lisa_m",
            "avatarThumb": "https://storage.googleapis.com/myinsta-6fc59.firebasestorage.app/ProfilePics/pexels-ron-lach-8159657.jpg"
          },
          "text": "Can't wait to see more!"
        }
      ]
    },
    {
      "id": "7",
      "user": {
        "id": "18",
        "name": "city_explorer",
        "avatarThumb": "https://storage.googleapis.com/myinsta-6fc59.firebasestorage.app/ProfilePics/pexels-sinileunen-6652928.jpg"
      },
      "caption": "City lights!",
      "media": [
        {
          "url": "https://storage.googleapis.com/myinsta-6fc59.firebasestorage.app/istockphoto-2156942049-1024x1024.jpg",
          "type": "image",
          "resolution": "1024x1024"
        },
        {
          "url": "https://storage.googleapis.com/myinsta-6fc59.firebasestorage.app/istockphoto-2157702110-640_adpp_is.mp4",
          "type": "video",
          "resolution": "640x360"
        }
      ],
      "likes": 250,
      "comments": [
        {
          "user": {
            "id": "19",
            "name": "mike_t",
            "avatarThumb": "https://storage.googleapis.com/myinsta-6fc59.firebasestorage.app/ProfilePics/pexels-sinileunen-6652959.jpg"
          },
          "text": "Stunning view!"
        },
        {
          "user": {
            "id": "20",
            "name": "sophia_r",
            "avatarThumb": "https://storage.googleapis.com/myinsta-6fc59.firebasestorage.app/ProfilePics/pexels-vazhnik-7562313.jpg"
          },
          "text": "Love the city vibe!"
        }
      ]
    },
    {
      "id": "8",
      "user": {
        "id": "1",
        "name": "wildlife_photographer",
        "avatarThumb": "https://storage.googleapis.com/myinsta-6fc59.firebasestorage.app/ProfilePics/pexels-a-darmel-7322232.jpg"
      },
      "caption": "In the wild!",
      "media": [
        {
          "url": "https://storage.googleapis.com/myinsta-6fc59.firebasestorage.app/istockphoto-2161147879-640_adpp_is.mp4",
          "type": "video",
          "resolution": "640x360"
        },
        {
          "url": "https://storage.googleapis.com/myinsta-6fc59.firebasestorage.app/istockphoto-2165462299-1024x1024.jpg",
          "type": "image",
          "resolution": "1024x1024"
        }
      ],
      "likes": 290,
      "comments": [
        {
          "user": {
            "id": "2",
            "name": "david_l",
            "avatarThumb": "https://storage.googleapis.com/myinsta-6fc59.firebasestorage.app/ProfilePics/pexels-alohaphotostudio-4890259.jpg"
          },
          "text": "Amazing capture!"
        },
        {
          "user": {
            "id": "3",
            "name": "emily_w",
            "avatarThumb": "https://storage.googleapis.com/myinsta-6fc59.firebasestorage.app/ProfilePics/pexels-anastasia-shuraeva-5704849.jpg"
          },
          "text": "Nature at its best!"
        }
      ]
    },
    {
      "id": "9",
      "user": {
        "id": "4",
        "name": "landscape_lover",
        "avatarThumb": "https://storage.googleapis.com/myinsta-6fc59.firebasestorage.app/ProfilePics/pexels-anastasia-shuraeva-6608313.jpg"
      },
      "caption": "Mountain peaks!",
      "media": [
        {
          "url": "https://storage.googleapis.com/myinsta-6fc59.firebasestorage.app/istockphoto-2165538486-1024x1024.jpg",
          "type": "image",
          "resolution": "1024x1024"
        },
        {
          "url": "https://storage.googleapis.com/myinsta-6fc59.firebasestorage.app/istockphoto-2166802703-1024x1024.jpg",
          "type": "image",
          "resolution": "1024x1024"
        }
      ],
      "likes": 310,
      "comments": [
        {
          "user": {
            "id": "5",
            "name": "oliver_t",
            "avatarThumb": "https://storage.googleapis.com/myinsta-6fc59.firebasestorage.app/ProfilePics/pexels-arthousestudio-4571943.jpg"
          },
          "text": "Breathtaking view!"
        },
        {
          "user": {
            "id": "6",
            "name": "ava_m",
            "avatarThumb": "https://storage.googleapis.com/myinsta-6fc59.firebasestorage.app/ProfilePics/pexels-arthousestudio-4640886.jpg"
          },
          "text": "I want to go there!"
        }
      ]
    },
    {
      "id": "10",
      "user": {
        "id": "7",
        "name": "ocean_lover",
        "avatarThumb": "https://storage.googleapis.com/myinsta-6fc59.firebasestorage.app/ProfilePics/pexels-darina-belonogova-7897152.jpg"
      },
      "caption": "Ocean waves!",
      "media": [
        {
          "url": "https://storage.googleapis.com/myinsta-6fc59.firebasestorage.app/istockphoto-2168127476-1024x1024.jpg",
          "type": "image",
          "resolution": "1024x1024"
        },
        {
          "url": "https://storage.googleapis.com/myinsta-6fc59.firebasestorage.app/istockphoto-2168171039-1024x1024.jpg",
          "type": "image",
          "resolution": "1024x1024"
        },
        {
          "url": "https://storage.googleapis.com/myinsta-6fc59.firebasestorage.app/istockphoto-2170889984-1024x1024.jpg",
          "type": "image",
          "resolution": "1024x1024"
        }
      ],
      "likes": 320,
      "comments": [
        {
          "user": {
            "id": "8",
            "name": "noah_s",
            "avatarThumb": "https://storage.googleapis.com/myinsta-6fc59.firebasestorage.app/ProfilePics/pexels-darina-belonogova-7897404.jpg"
          },
          "text": "So peaceful!"
        },
        {
          "user": {
            "id": "9",
            "name": "mia_r",
            "avatarThumb": "https://storage.googleapis.com/myinsta-6fc59.firebasestorage.app/ProfilePics/pexels-guilhermealmeida-1858175.jpg"
          },
          "text": "Love the ocean!"
        }
      ]
    }
  ]
}
